raggie/__init__.py
raggie/data.py
raggie/main.py
raggie/model.py
raggie/types.py
raggie/utils.py
raggie-0.2.0.dist-info/licenses/LICENSE
raggie-0.2.0.dist-info/METADATA
raggie-0.2.0.dist-info/WHEEL
raggie-0.2.0.dist-info/top_level.txt
raggie-0.2.0.dist-info/RECORD
