Metadata-Version: 2.4
Name: raggie
Version: 0.2.0
Summary: Add your description here
Home-page: https://yamaceay.github.io/raggie/raggie.html
Author: Yamac Eren Ay
Author-email: yamacerenay2001@gmail.com
Platform: any
Requires-Python: >=3.6
License-File: LICENSE
Requires-Dist: accelerate~=1.7.0
Requires-Dist: datasets<5.0.0,>=3.6.0
Requires-Dist: faiss-cpu~=1.11.0
Requires-Dist: matplotlib~=3.9.2
Requires-Dist: numpy~=2.3.0
Requires-Dist: scikit-learn~=1.5.2
Requires-Dist: scipy~=1.15.3
Requires-Dist: seaborn~=0.13.2
Requires-Dist: sentence-transformers~=4.1.0
Requires-Dist: torch~=2.5.1
Dynamic: author
Dynamic: author-email
Dynamic: home-page
Dynamic: license-file
Dynamic: platform
Dynamic: requires-python
